dmypy_ls/__init__.py
dmypy_ls/tests/__init__.py
dmypy_ls/tests/test_dmypy_ls.py
dmypy_ls-1.13.dist-info/LICENSE
dmypy_ls-1.13.dist-info/METADATA
dmypy_ls-1.13.dist-info/WHEEL
dmypy_ls-1.13.dist-info/entry_points.txt
dmypy_ls-1.13.dist-info/RECORD
