Metadata-Version: 2.1
Name: dmypy-ls
Version: 1.13
Summary: super fast mypy language server
Home-page: https://github.com/sileht/dmypy-ls
Author: Mehdi Abaakouk
Author-email: sileht@sileht.net
Requires-Python: >=3.9,<4
Classifier: Development Status :: 4 - Beta
Classifier: Environment :: Console
Classifier: Intended Audience :: Developers
Classifier: License :: OSI Approved :: MIT License
Classifier: Operating System :: POSIX
Classifier: Programming Language :: Python
Classifier: Programming Language :: Python :: 3
Classifier: Programming Language :: Python :: 3.9
Classifier: Programming Language :: Python :: 3.10
Classifier: Programming Language :: Python :: 3.11
Classifier: Topic :: Software Development
Requires-Dist: mypy
Requires-Dist: pygls (>=1.0.1)
